Workbook

Sheet PACIENTES
A1: 🌿 NutriAge · Base de Datos de Pacientes · Fernanda Ugarte
A2: Registro principal de pacientes — sincronizar con Google Sheets
A3: Ticket | B3: Nombre Completo | C3: Email | D3: Teléfono | E3: RUT / ID | F3: Edad | G3: Ocupación | H3: Peso (kg) | I3: Talla (m) | J3: IMC | K3: Motivo Consulta | L3: Fecha Cita | M3: Hora Cita | N3: Estado | O3: Comprobante | P3: WA Notificado | Q3: Fecha Registro | R3: Notas Internas
J4: =IF(AND(H4<>"",I4<>""),ROUND(H4/(I4^2),1),"")
J5: =IF(AND(H5<>"",I5<>""),ROUND(H5/(I5^2),1),"")
J6: =IF(AND(H6<>"",I6<>""),ROUND(H6/(I6^2),1),"")
J7: =IF(AND(H7<>"",I7<>""),ROUND(H7/(I7^2),1),"")
J8: =IF(AND(H8<>"",I8<>""),ROUND(H8/(I8^2),1),"")
J9: =IF(AND(H9<>"",I9<>""),ROUND(H9/(I9^2),1),"")
J10: =IF(AND(H10<>"",I10<>""),ROUND(H10/(I10^2),1),"")
J11: =IF(AND(H11<>"",I11<>""),ROUND(H11/(I11^2),1),"")
J12: =IF(AND(H12<>"",I12<>""),ROUND(H12/(I12^2),1),"")
J13: =IF(AND(H13<>"",I13<>""),ROUND(H13/(I13^2),1),"")
J14: =IF(AND(H14<>"",I14<>""),ROUND(H14/(I14^2),1),"")
J15: =IF(AND(H15<>"",I15<>""),ROUND(H15/(I15^2),1),"")
... J33: =IF(AND(H33<>"",I33<>""),ROUND(H33/(I33^2),1),"")
A34: TOTALES
A36: RESUMEN AUTOMÁTICO
A37: Total pacientes registrados | I37: =COUNTA(A4:A33)
A38: Citas confirmadas | I38: =COUNTIF(N4:N33,"Confirmado")
A39: Citas completadas | I39: =COUNTIF(N4:N33,"Completado")
A40: Citas pendientes | I40: =COUNTIF(N4:N33,"Pendiente")
A41: Citas canceladas | I41: =COUNTIF(N4:N33,"Cancelado")
A42: Comprobantes recibidos | I42: =COUNTIF(O4:O33,"Sí")
A43: IMC promedio pacientes | I43: =IFERROR(AVERAGE(J4:J33),"—")
A44: Ingresos estimados ($15.000 c/u) | I44: =COUNTIF(N4:N33,"Completado")*15000

Sheet FORMULARIO_CLINICO
A1: 🩺 Formulario Clínico — Anamnesis Nutricional
A2: Datos del cuestionario de ingreso — 1 fila por paciente
A3: IDENTIFICACIÓN | J3: ANAMNESIS MÉDICA | O3: ESTILO DE VIDA | U3: ALERGIAS Y SUPLEMENTOS | W3: CONSUMO SUSTANCIAS | Y3: DIGESTIÓN | Z3: FRECUENCIA SEMANAL | AG3: REGISTRO 24H | AH3: CITA
A4: Ticket | B4: Nombre | C4: Email | D4: Teléfono | E4: RUT/ID | F4: Edad | G4: Ocupación | H4: Peso(kg) | I4: Talla(m) | J4: Enfermedades | K4: Lesiones | L4: Antec. Familiar | M4: Cirugías | N4: Convivencia | O4: Act. Física | P4: Horario Act. | Q4: Horas Sueño | R4: No le gusta | S4: Almuerzo habitual | T4: Horario comidas | U4: Alergias/Intol. | V4: Suplementos | W4: Alcohol | X4: Tabaco/Drogas | Y4: Síntomas GI | Z4: Cereales | AA4: Legumbres | AB4: Pescado | AC4: Fruta | AD4: Verduras | AE4: Dulces | AF4: Lácteos | AG4: Registro 24 horas | AH4: Motivo consulta | AI4: Fecha cita | AJ4: Hora cita | AK4: Estado | AL4: Comprobante

Sheet CITAS
A1: 📅 Gestión de Citas — NutriAge
A2: Registro de todas las citas agendadas, confirmadas y realizadas
A3: Ticket | B3: Nombre Paciente | C3: Email | D3: Teléfono | E3: Fecha Cita | F3: Hora Inicio | G3: Duración (min) | H3: Modalidad | I3: Estado | J3: Sala Jitsi | K3: WA Paciente Enviado | L3: WA Nutri Enviado | M3: Notas Post-Consulta
G4: 45
G5: 45
G6: 45
G7: 45
G8: 45
G9: 45
G10: 45
G11: 45
G12: 45
G13: 45
G14: 45
G15: 45
... G53: 45

Sheet PAGOS
A1: 💰 Registro de Pagos y Transferencias
A2: Control de comprobantes, estados de pago e ingresos
A3: Ticket | B3: Nombre Paciente | C3: Fecha Cita | D3: Monto ($CLP) | E3: Método Pago | F3: Estado Pago | G3: Fecha Transferencia | H3: Comprobante Recibido | I3: Nombre Archivo Comprobante | J3: RUT Titular Pago | K3: Banco Origen | L3: Notas
D4: 15000
D5: 15000
D6: 15000
D7: 15000
D8: 15000
D9: 15000
D10: 15000
D11: 15000
D12: 15000
D13: 15000
D14: 15000
D15: 15000
... D53: 15000
A55: TOTAL INGRESOS VERIFICADOS | D55: =SUMIF(F4:F53,"Verificado",D4:D53)
A56: TOTAL INGRESOS RECIBIDOS (no verificados) | D56: =SUMIF(F4:F53,"Recibido",D4:D53)

Sheet DISPONIBILIDAD
A1: 🗓️ Disponibilidad Semanal — Horarios Habilitados
A2: Define los horarios disponibles para agendar. Modificar aquí refleja automáticamente en el sitio web.
A3: Fecha | B3: Día Semana | C3: Hora | D3: Disponible | E3: Reservado por (Ticket) | F3: Nombre Paciente | G3: Tipo Bloqueo | H3: Motivo Bloqueo | I3: Notas
A4: 2026-04-10 | B4: Viernes | C4: 09:00 | D4: Sí
A5: 2026-04-10 | B5: Viernes | C5: 09:45 | D5: Sí
A6: 2026-04-10 | B6: Viernes | C6: 10:30 | D6: Sí
A7: 2026-04-10 | B7: Viernes | C7: 11:15 | D7: Sí
A8: 2026-04-10 | B8: Viernes | C8: 12:00 | D8: Sí
A9: 2026-04-10 | B9: Viernes | C9: 15:00 | D9: Sí
A10: 2026-04-10 | B10: Viernes | C10: 15:45 | D10: Sí
A11: 2026-04-10 | B11: Viernes | C11: 16:30 | D11: Sí
A12: 2026-04-10 | B12: Viernes | C12: 17:15 | D12: Sí
A13: 2026-04-13 | B13: Lunes | C13: 09:00 | D13: Sí
A14: 2026-04-13 | B14: Lunes | C14: 09:45 | D14: Sí
A15: 2026-04-13 | B15: Lunes | C15: 10:30 | D15: Sí
... A200: 2026-05-11 | B200: Lunes | C200: 16:30 | D200: Sí

Sheet VIDEOLLAMADAS
A1: 📹 Registro de Videollamadas — Jitsi Meet
A2: Log de sesiones de telemedicina — sala, duración, estado de conexión
A3: Ticket | B3: Nombre Paciente | C3: Fecha | D3: Hora Inicio | E3: Hora Fin | F3: Duración Real (min) | G3: Sala Jitsi | H3: Estado Llamada | I3: Grabación Disponible | J3: Calidad Conexión | K3: Notas
F4: =IF(AND(D4<>"",E4<>""),ROUND((E4-D4)*1440,0),"")
F5: =IF(AND(D5<>"",E5<>""),ROUND((E5-D5)*1440,0),"")
F6: =IF(AND(D6<>"",E6<>""),ROUND((E6-D6)*1440,0),"")
F7: =IF(AND(D7<>"",E7<>""),ROUND((E7-D7)*1440,0),"")
F8: =IF(AND(D8<>"",E8<>""),ROUND((E8-D8)*1440,0),"")
F9: =IF(AND(D9<>"",E9<>""),ROUND((E9-D9)*1440,0),"")
F10: =IF(AND(D10<>"",E10<>""),ROUND((E10-D10)*1440,0),"")
F11: =IF(AND(D11<>"",E11<>""),ROUND((E11-D11)*1440,0),"")
F12: =IF(AND(D12<>"",E12<>""),ROUND((E12-D12)*1440,0),"")
F13: =IF(AND(D13<>"",E13<>""),ROUND((E13-D13)*1440,0),"")
F14: =IF(AND(D14<>"",E14<>""),ROUND((E14-D14)*1440,0),"")
F15: =IF(AND(D15<>"",E15<>""),ROUND((E15-D15)*1440,0),"")
... F53: =IF(AND(D53<>"",E53<>""),ROUND((E53-D53)*1440,0),"")

Sheet DASHBOARD
A1: 📊 NutriAge · Dashboard de Métricas
A2: Actualización automática — fórmulas vinculadas a hojas PACIENTES, CITAS y PAGOS
A4: 👥 PACIENTES | D4: 📅 CITAS | G4: 💰 INGRESOS | J4: 📹 LLAMADAS
A5: Total registrados | B5: =COUNTA(PACIENTES!A4:A500) | D5: Total citas | E5: =COUNTA(CITAS!A4:A500) | G5: Total verificado | H5: =SUMIF(PAGOS!F4:F500,"Verificado",PAGOS!D4:D500) | J5: Total sesiones | K5: =COUNTA(VIDEOLLAMADAS!A4:A500)
A6: Nuevos este mes | B6: =COUNTIFS(PACIENTES!Q4:Q500,">="&DATE(YEAR(TODAY()),MONTH(TODAY()),1)) | D6: Confirmadas | E6: =COUNTIF(CITAS!I4:I500,"Confirmado") | G6: Total recibido | H6: =SUMIF(PAGOS!F4:F500,"Recibido",PAGOS!D4:D500) | J6: Exitosas | K6: =COUNTIF(VIDEOLLAMADAS!H4:H500,"Exitosa")
A7: IMC promedio | B7: =IFERROR(AVERAGE(PACIENTES!J4:J500),"—") | D7: Completadas | E7: =COUNTIF(CITAS!I4:I500,"Completado") | G7: Pendiente cobro | H7: =COUNTIF(PAGOS!F4:F500,"Pendiente")*15000 | J7: Duración prom (min) | K7: =IFERROR(AVERAGE(VIDEOLLAMADAS!F4:F500),"—")

Sheet CONFIG_GAS
A1: ⚙️ Configuración Google Apps Script
A3: PARÁMETRO | B3: VALOR | C3: DESCRIPCIÓN
A4: SPREADSHEET_ID | B4: <PEGAR_ID_DE_GOOGLE_SHEETS> | C4: ID del documento Google Sheets (URL: .../d/<ID>/edit)
A5: SHEET_PACIENTES | B5: PACIENTES | C5: Nombre exacto de la hoja de pacientes
A6: SHEET_FORM | B6: FORMULARIO_CLINICO | C6: Hoja del formulario clínico
A7: SHEET_CITAS | B7: CITAS | C7: Hoja de citas
A8: SHEET_PAGOS | B8: PAGOS | C8: Hoja de pagos
A9: SHEET_DISP | B9: DISPONIBILIDAD | C9: Hoja de disponibilidad
A10: SHEET_VIDEO | B10: VIDEOLLAMADAS | C10: Hoja de videollamadas
A11: PRECIO_CONSULTA | B11: 15000 | C11: Valor de la consulta en CLP
A12: NUTRI_EMAIL | B12: nutricionista@email.com | C12: Email de Fernanda para notificaciones
A13: NUTRI_WA | B13: 56912345678 | C13: WhatsApp de Fernanda (formato internacional)
A14: TICKET_PREFIX | B14: NA | C14: Prefijo de tickets (NA-YYYYMMDD-NNN)
... A19: GAS_WEB_APP_URL | B19: <PEGAR_URL_DEL_WEB_APP> | C19: URL del Google Apps Script publicado como Web App
A22: ENDPOINTS GOOGLE APPS SCRIPT (Web App)
A23: Método | B23: Acción GAS | C23: Descripción
A24: GET ?action=getAvailability | B24: doGet(e) | C24: Retorna JSON con fechas y horarios disponibles
A25: POST action=registerPatient | B25: doPost(e) | C25: Registra nuevo paciente + cita + formulario
A26: POST action=uploadComprobante | B26: doPost(e) | C26: Guarda el nombre del archivo comprobante
A27: GET ?action=getPatientByTicket | B27: doGet(e) | C27: Busca paciente por número de ticket
A28: GET ?action=getAvailabilityByDate | B28: doGet(e) | C28: Retorna slots disponibles para una fecha
A29: POST action=updateCitaStatus | B29: doPost(e) | C29: Actualiza estado de cita (nutri/admin)
A30: GET ?action=getDashboard | B30: doGet(e) | C30: Retorna métricas del dashboard para admin
A31: POST action=blockSlot | B31: doPost(e) | C31: Bloquea un horario desde panel de nutri

Sheet IDEAS_MEJORAS
A1: 💡 Ideas de Mejora para NutriAge
A3: PRIORIDAD | B3: CATEGORÍA | C3: IDEA / FUNCIONALIDAD | D3: IMPACTO | E3: ESFUERZO
A4: 🔴 Alta | B4: Autenticación | C4: Reemplazar login por ticket con autenticación real (Google/Magic Link). El paciente tiene su cuenta persistente con historial de sesiones. | D4: Alto | E4: Medio
A5: 🔴 Alta | B5: Base de datos | C5: Migrar de localStorage a Google Sheets como única fuente de verdad. GAS actúa como API REST. | D5: Alto | E5: Medio
A6: 🔴 Alta | B6: Pagos | C6: Integrar pasarela de pago (Mercado Pago / Webpay). El pago confirma la cita automáticamente sin subida manual de comprobante. | D6: Alto | E6: Alto
A7: 🔴 Alta | B7: Notificaciones | C7: Email automático de confirmación al paciente al reservar (via GAS + Gmail API). Incluir ticket, fecha, sala Jitsi. | D7: Alto | E7: Bajo
A8: 🟡 Media | B8: Recordatorios | C8: Recordatorio automático por email + WhatsApp 24h y 1h antes de la cita. | D8: Alto | E8: Medio
A9: 🟡 Media | B9: Plan alimentario | C9: Módulo de carga/descarga de plan de alimentación personalizado en PDF directamente desde el panel de Fernanda. | D9: Alto | E9: Medio
A10: 🟡 Media | B10: Ficha clínica | C10: Historial de consultas: cada paciente puede tener múltiples sesiones con evolución de IMC, peso y notas. | D10: Alto | E10: Alto
A11: 🟡 Media | B11: Re-agendamiento | C11: Permitir al paciente re-agendar desde su panel usando su ticket (hasta X horas antes). | D11: Medio | E11: Medio
A12: 🟡 Media | B12: Panel admin | C12: Dashboard con gráficos de evolución de ingresos, pacientes por mes, motivos de consulta más frecuentes. | D12: Medio | E12: Medio
A13: 🟡 Media | B13: Recetas/Recursos | C13: Biblioteca de recetas y recursos nutricionales descargables desde el panel del paciente. | D13: Medio | E13: Bajo
A14: 🟢 Baja | B14: SEO/Landing | C14: Separar landing page del sistema de agendamiento. La landing pública presenta a Fernanda; el sistema está detrás de login. | D14: Medio | E14: Bajo
... A23: 🔵 Futuro | B23: Multi-profesional | C23: Escalabilidad a varios nutricionistas con panel de administración central. | D23: Alto | E23: Alto
